hpi_purarue-0.1.0.dist-info/licenses/LICENSE
my/bash.py
my/ipython.py
my/project_euler.py
my/py.typed
my/ttt.py
my/zsh.py
my/activitywatch/active_window.py
my/apple/privacy_export.py
my/blizzard/gdpr.py
my/chess/export.py
my/discord/data_export.py
my/facebook/gdpr.py
my/grouvee/export.py
my/ip/all.py
my/ip/blizzard.py
my/ip/discord.py
my/ip/facebook.py
my/league/export.py
my/linkedin/privacy_export.py
my/listenbrainz/export.py
my/location/apple.py
my/mail/all.py
my/mail/common.py
my/mail/imap.py
my/mail/mbox.py
my/mail/parse_parts.py
my/mal/export.py
my/minecraft/advancements.py
my/mpv/history_daemon.py
my/offline/listens.py
my/piazza/scraper.py
my/rss/newsboat/git_history.py
my/runelite/screenshots.py
my/scramble/history.py
my/skype/gdpr.py
my/spotify/gdpr.py
my/steam/scraper.py
my/todotxt/active.py
my/todotxt/common.py
my/todotxt/git_history.py
my/trakt/export.py
my/twitch/all.py
my/twitch/common.py
my/twitch/gdpr.py
my/twitch/overrustle_logs.py
my/utils/parse_csv.py
my/utils/time.py
my/utils/backup_to/__main__.py
hpi_purarue-0.1.0.dist-info/METADATA
hpi_purarue-0.1.0.dist-info/WHEEL
hpi_purarue-0.1.0.dist-info/entry_points.txt
hpi_purarue-0.1.0.dist-info/top_level.txt
hpi_purarue-0.1.0.dist-info/RECORD
