Metadata-Version: 2.4
Name: HPI_purarue
Version: 0.1.0
Summary: A Python interface to my life
Author: purarue
License-Expression: MIT
Project-URL: Homepage, https://github.com/purarue/HPI
Classifier: Operating System :: OS Independent
Classifier: Programming Language :: Python :: 3
Classifier: Programming Language :: Python :: 3 :: Only
Classifier: Programming Language :: Python :: 3.12
Classifier: Programming Language :: Python :: 3.13
Requires-Python: >=3.12
License-File: LICENSE
Dynamic: license-file
